{
  "AWSTemplateFormatVersion": "2010-09-09",
  "Description": "The AWS CloudFormation template for this Serverless application",
  "Resources": {
    "ApiLogGroup": {
      "Type": "AWS::Logs::LogGroup",
      "Properties": {
        "LogGroupName": "/aws/lambda/sandytest-dev-api"
      }
    },
    "GetCustomersLogGroup": {
      "Type": "AWS::Logs::LogGroup",
      "Properties": {
        "LogGroupName": "/aws/lambda/sandytest-dev-getCustomers"
      }
    },
    "CreateCustomerLogGroup": {
      "Type": "AWS::Logs::LogGroup",
      "Properties": {
        "LogGroupName": "/aws/lambda/sandytest-dev-createCustomer"
      }
    },
    "IamRoleLambdaExecution": {
      "Type": "AWS::IAM::Role",
      "Properties": {
        "AssumeRolePolicyDocument": {
          "Version": "2012-10-17",
          "Statement": [
            {
              "Effect": "Allow",
              "Principal": {
                "Service": [
                  "lambda.amazonaws.com"
                ]
              },
              "Action": [
                "sts:AssumeRole"
              ]
            }
          ]
        },
        "Policies": [
          {
            "PolicyName": {
              "Fn::Join": [
                "-",
                [
                  "sandytest",
                  "dev",
                  "lambda"
                ]
              ]
            },
            "PolicyDocument": {
              "Version": "2012-10-17",
              "Statement": [
                {
                  "Effect": "Allow",
                  "Action": [
                    "logs:CreateLogStream",
                    "logs:CreateLogGroup",
                    "logs:TagResource"
                  ],
                  "Resource": [
                    {
                      "Fn::Sub": "arn:${AWS::Partition}:logs:${AWS::Region}:${AWS::AccountId}:log-group:/aws/lambda/sandytest-dev*:*"
                    }
                  ]
                },
                {
                  "Effect": "Allow",
                  "Action": [
                    "logs:PutLogEvents"
                  ],
                  "Resource": [
                    {
                      "Fn::Sub": "arn:${AWS::Partition}:logs:${AWS::Region}:${AWS::AccountId}:log-group:/aws/lambda/sandytest-dev*:*:*"
                    }
                  ]
                },
                {
                  "Effect": "Allow",
                  "Action": [
                    "dynamodb:PutItem",
                    "dynamodb:Get*",
                    "dynamodb:Scan*",
                    "dynamodb:UpdateItem",
                    "dynamodb:DeleteItem"
                  ],
                  "Resource": "arn:aws:dynamodb:us-east-1:193962410929:table/sandytest-customerTable-dev"
                }
              ]
            }
          }
        ],
        "Path": "/",
        "RoleName": {
          "Fn::Join": [
            "-",
            [
              "sandytest",
              "dev",
              {
                "Ref": "AWS::Region"
              },
              "lambdaRole"
            ]
          ]
        }
      }
    },
    "ApiLambdaFunction": {
      "Type": "AWS::Lambda::Function",
      "Properties": {
        "Code": {
          "S3Bucket": "serverless-framework-deployments-us-east-1-447ed499-7f7f",
          "S3Key": "serverless/sandytest/dev/1730862878664-2024-11-06T03:14:38.664Z/sandytest.zip"
        },
        "Handler": "index.handler",
        "Runtime": "nodejs18.x",
        "FunctionName": "sandytest-dev-api",
        "MemorySize": 1024,
        "Timeout": 6,
        "Environment": {
          "Variables": {
            "DYNAMODB_CUSTOMER_TABLE": "sandytest-customerTable-dev"
          }
        },
        "Role": {
          "Fn::GetAtt": [
            "IamRoleLambdaExecution",
            "Arn"
          ]
        }
      },
      "DependsOn": [
        "ApiLogGroup"
      ]
    },
    "GetCustomersLambdaFunction": {
      "Type": "AWS::Lambda::Function",
      "Properties": {
        "Code": {
          "S3Bucket": "serverless-framework-deployments-us-east-1-447ed499-7f7f",
          "S3Key": "serverless/sandytest/dev/1730862878664-2024-11-06T03:14:38.664Z/sandytest.zip"
        },
        "Handler": "getCustomers.getCustomers",
        "Runtime": "nodejs18.x",
        "FunctionName": "sandytest-dev-getCustomers",
        "MemorySize": 1024,
        "Timeout": 6,
        "Environment": {
          "Variables": {
            "DYNAMODB_CUSTOMER_TABLE": "sandytest-customerTable-dev"
          }
        },
        "Role": {
          "Fn::GetAtt": [
            "IamRoleLambdaExecution",
            "Arn"
          ]
        }
      },
      "DependsOn": [
        "GetCustomersLogGroup"
      ]
    },
    "CreateCustomerLambdaFunction": {
      "Type": "AWS::Lambda::Function",
      "Properties": {
        "Code": {
          "S3Bucket": "serverless-framework-deployments-us-east-1-447ed499-7f7f",
          "S3Key": "serverless/sandytest/dev/1730862878664-2024-11-06T03:14:38.664Z/sandytest.zip"
        },
        "Handler": "createCustomer.createCustomer",
        "Runtime": "nodejs18.x",
        "FunctionName": "sandytest-dev-createCustomer",
        "MemorySize": 1024,
        "Timeout": 6,
        "Environment": {
          "Variables": {
            "DYNAMODB_CUSTOMER_TABLE": "sandytest-customerTable-dev"
          }
        },
        "Role": {
          "Fn::GetAtt": [
            "IamRoleLambdaExecution",
            "Arn"
          ]
        }
      },
      "DependsOn": [
        "CreateCustomerLogGroup"
      ]
    },
    "ApiLambdaVersionKRshIvpjBs1OKVzPnHb4tBmWO6hIrPB2DwgRLZEU": {
      "Type": "AWS::Lambda::Version",
      "DeletionPolicy": "Retain",
      "Properties": {
        "FunctionName": {
          "Ref": "ApiLambdaFunction"
        },
        "CodeSha256": "wZ0AKhJOewhlJm0z0MEd6yl0kknDOc/Msb0dJfy1kx8="
      }
    },
    "GetCustomersLambdaVersiondDguv3NZtXv2V5qQBgfeUTCPN8GbsuXZmij4BGJkWM": {
      "Type": "AWS::Lambda::Version",
      "DeletionPolicy": "Retain",
      "Properties": {
        "FunctionName": {
          "Ref": "GetCustomersLambdaFunction"
        },
        "CodeSha256": "wZ0AKhJOewhlJm0z0MEd6yl0kknDOc/Msb0dJfy1kx8="
      }
    },
    "CreateCustomerLambdaVersionrMGtsDfsYHZpMdhr16z93VXb2lb4rpeyJxZ7GkbLJqo": {
      "Type": "AWS::Lambda::Version",
      "DeletionPolicy": "Retain",
      "Properties": {
        "FunctionName": {
          "Ref": "CreateCustomerLambdaFunction"
        },
        "CodeSha256": "wZ0AKhJOewhlJm0z0MEd6yl0kknDOc/Msb0dJfy1kx8="
      }
    },
    "HttpApi": {
      "Type": "AWS::ApiGatewayV2::Api",
      "Properties": {
        "Name": "dev-sandytest",
        "ProtocolType": "HTTP"
      }
    },
    "HttpApiStage": {
      "Type": "AWS::ApiGatewayV2::Stage",
      "Properties": {
        "ApiId": {
          "Ref": "HttpApi"
        },
        "StageName": "$default",
        "AutoDeploy": true,
        "DefaultRouteSettings": {
          "DetailedMetricsEnabled": false
        }
      }
    },
    "ApiLambdaPermissionHttpApi": {
      "Type": "AWS::Lambda::Permission",
      "Properties": {
        "FunctionName": {
          "Fn::GetAtt": [
            "ApiLambdaFunction",
            "Arn"
          ]
        },
        "Action": "lambda:InvokeFunction",
        "Principal": "apigateway.amazonaws.com",
        "SourceArn": {
          "Fn::Join": [
            "",
            [
              "arn:",
              {
                "Ref": "AWS::Partition"
              },
              ":execute-api:",
              {
                "Ref": "AWS::Region"
              },
              ":",
              {
                "Ref": "AWS::AccountId"
              },
              ":",
              {
                "Ref": "HttpApi"
              },
              "/*"
            ]
          ]
        }
      }
    },
    "HttpApiIntegrationApi": {
      "Type": "AWS::ApiGatewayV2::Integration",
      "Properties": {
        "ApiId": {
          "Ref": "HttpApi"
        },
        "IntegrationType": "AWS_PROXY",
        "IntegrationUri": {
          "Fn::GetAtt": [
            "ApiLambdaFunction",
            "Arn"
          ]
        },
        "PayloadFormatVersion": "2.0",
        "TimeoutInMillis": 30000
      }
    },
    "HttpApiRouteGet": {
      "Type": "AWS::ApiGatewayV2::Route",
      "Properties": {
        "ApiId": {
          "Ref": "HttpApi"
        },
        "RouteKey": "GET /",
        "Target": {
          "Fn::Join": [
            "/",
            [
              "integrations",
              {
                "Ref": "HttpApiIntegrationApi"
              }
            ]
          ]
        }
      },
      "DependsOn": "HttpApiIntegrationApi"
    },
    "GetCustomersLambdaPermissionHttpApi": {
      "Type": "AWS::Lambda::Permission",
      "Properties": {
        "FunctionName": {
          "Fn::GetAtt": [
            "GetCustomersLambdaFunction",
            "Arn"
          ]
        },
        "Action": "lambda:InvokeFunction",
        "Principal": "apigateway.amazonaws.com",
        "SourceArn": {
          "Fn::Join": [
            "",
            [
              "arn:",
              {
                "Ref": "AWS::Partition"
              },
              ":execute-api:",
              {
                "Ref": "AWS::Region"
              },
              ":",
              {
                "Ref": "AWS::AccountId"
              },
              ":",
              {
                "Ref": "HttpApi"
              },
              "/*"
            ]
          ]
        }
      }
    },
    "HttpApiIntegrationGetCustomers": {
      "Type": "AWS::ApiGatewayV2::Integration",
      "Properties": {
        "ApiId": {
          "Ref": "HttpApi"
        },
        "IntegrationType": "AWS_PROXY",
        "IntegrationUri": {
          "Fn::GetAtt": [
            "GetCustomersLambdaFunction",
            "Arn"
          ]
        },
        "PayloadFormatVersion": "2.0",
        "TimeoutInMillis": 30000
      }
    },
    "HttpApiRouteGetCustomers": {
      "Type": "AWS::ApiGatewayV2::Route",
      "Properties": {
        "ApiId": {
          "Ref": "HttpApi"
        },
        "RouteKey": "GET /customers",
        "Target": {
          "Fn::Join": [
            "/",
            [
              "integrations",
              {
                "Ref": "HttpApiIntegrationGetCustomers"
              }
            ]
          ]
        }
      },
      "DependsOn": "HttpApiIntegrationGetCustomers"
    },
    "CreateCustomerLambdaPermissionHttpApi": {
      "Type": "AWS::Lambda::Permission",
      "Properties": {
        "FunctionName": {
          "Fn::GetAtt": [
            "CreateCustomerLambdaFunction",
            "Arn"
          ]
        },
        "Action": "lambda:InvokeFunction",
        "Principal": "apigateway.amazonaws.com",
        "SourceArn": {
          "Fn::Join": [
            "",
            [
              "arn:",
              {
                "Ref": "AWS::Partition"
              },
              ":execute-api:",
              {
                "Ref": "AWS::Region"
              },
              ":",
              {
                "Ref": "AWS::AccountId"
              },
              ":",
              {
                "Ref": "HttpApi"
              },
              "/*"
            ]
          ]
        }
      }
    },
    "HttpApiIntegrationCreateCustomer": {
      "Type": "AWS::ApiGatewayV2::Integration",
      "Properties": {
        "ApiId": {
          "Ref": "HttpApi"
        },
        "IntegrationType": "AWS_PROXY",
        "IntegrationUri": {
          "Fn::GetAtt": [
            "CreateCustomerLambdaFunction",
            "Arn"
          ]
        },
        "PayloadFormatVersion": "2.0",
        "TimeoutInMillis": 30000
      }
    },
    "HttpApiRoutePostCustomer": {
      "Type": "AWS::ApiGatewayV2::Route",
      "Properties": {
        "ApiId": {
          "Ref": "HttpApi"
        },
        "RouteKey": "POST /customer",
        "Target": {
          "Fn::Join": [
            "/",
            [
              "integrations",
              {
                "Ref": "HttpApiIntegrationCreateCustomer"
              }
            ]
          ]
        }
      },
      "DependsOn": "HttpApiIntegrationCreateCustomer"
    },
    "CustomerTable": {
      "Type": "AWS::DynamoDB::Table",
      "Properties": {
        "AttributeDefinitions": [
          {
            "AttributeName": "primary_key",
            "AttributeType": "S"
          }
        ],
        "BillingMode": "PAY_PER_REQUEST",
        "KeySchema": [
          {
            "AttributeName": "primary_key",
            "KeyType": "HASH"
          }
        ],
        "TableName": "sandytest-customerTable-dev"
      }
    }
  },
  "Outputs": {
    "ServerlessDeploymentBucketName": {
      "Value": "serverless-framework-deployments-us-east-1-447ed499-7f7f",
      "Export": {
        "Name": "sls-sandytest-dev-ServerlessDeploymentBucketName"
      }
    },
    "ApiLambdaFunctionQualifiedArn": {
      "Description": "Current Lambda function version",
      "Value": {
        "Ref": "ApiLambdaVersionKRshIvpjBs1OKVzPnHb4tBmWO6hIrPB2DwgRLZEU"
      },
      "Export": {
        "Name": "sls-sandytest-dev-ApiLambdaFunctionQualifiedArn"
      }
    },
    "GetCustomersLambdaFunctionQualifiedArn": {
      "Description": "Current Lambda function version",
      "Value": {
        "Ref": "GetCustomersLambdaVersiondDguv3NZtXv2V5qQBgfeUTCPN8GbsuXZmij4BGJkWM"
      },
      "Export": {
        "Name": "sls-sandytest-dev-GetCustomersLambdaFunctionQualifiedArn"
      }
    },
    "CreateCustomerLambdaFunctionQualifiedArn": {
      "Description": "Current Lambda function version",
      "Value": {
        "Ref": "CreateCustomerLambdaVersionrMGtsDfsYHZpMdhr16z93VXb2lb4rpeyJxZ7GkbLJqo"
      },
      "Export": {
        "Name": "sls-sandytest-dev-CreateCustomerLambdaFunctionQualifiedArn"
      }
    },
    "HttpApiId": {
      "Description": "Id of the HTTP API",
      "Value": {
        "Ref": "HttpApi"
      },
      "Export": {
        "Name": "sls-sandytest-dev-HttpApiId"
      }
    },
    "HttpApiUrl": {
      "Description": "URL of the HTTP API",
      "Value": {
        "Fn::Join": [
          "",
          [
            "https://",
            {
              "Ref": "HttpApi"
            },
            ".execute-api.",
            {
              "Ref": "AWS::Region"
            },
            ".",
            {
              "Ref": "AWS::URLSuffix"
            }
          ]
        ]
      },
      "Export": {
        "Name": "sls-sandytest-dev-HttpApiUrl"
      }
    }
  }
}